pash/__init__.py
pash/api.py
pash/arg_parse.py
pash/file_info.py
pash/ls_class.py
pash_src/__init__.py
pash_src/api.py
pash_src/arg_parse.py
pash_src/file_info.py
pash_src/ls.py
pash_src/ls_class.py
pash_src/run_tests.py
pash-0.0.3.dist-info/LICENSE
pash-0.0.3.dist-info/METADATA
pash-0.0.3.dist-info/WHEEL
pash-0.0.3.dist-info/top_level.txt
pash-0.0.3.dist-info/RECORD
