Metadata-Version: 2.1
Name: pash
Version: 0.0.3
Summary: Implement Bash command with Python
Home-page: https://github.com/Windsooon/pash
Author: Windson Yang
Author-email: wiwindson@outlook.com
License: MIT
Keywords: bash ls
Platform: UNKNOWN
Classifier: License :: OSI Approved :: MIT License
Classifier: Programming Language :: Python :: 3.5
Classifier: Programming Language :: Python :: 3.6
